{"metadata":{"Copyright":"(c) 2019 College of American Pathologists.  All rights reserved.  License required for use.","GenericHeaderText":"Surgical Pathology Cancer Case Summary","Category":"Digestive System","OfficialName":"APPENDIX: Resection","CAP_ProtocolName":"Appendix","CAP_ProtocolShortName":"Appendix","CAP_ProtocolVersion":"4.0.0.1","TemplateID":135.1000043,"Restrictions":"Please refer to the cancer protocol cover page (www.cap.org/cancerprotocols) for information about which tumor types and procedures can be reported using this template.","CAP_Required":true,"AccreditationDate":"2/28/2018","WebPostingDate":"2/27/2019","ReleaseStatus":"REL","AJCC_Version":"8th Edition"},"SDCFormId":"Appendix.Res.135_3.002.001.REL_sdcFDF","version":"3.002.001.REL","title":"APPENDIX: Resection","body":{"minRepetitions":1,"maxRepetitions":1,"sections":[{"title":"SPECIMEN (Note A)","minRepetitions":1,"maxRepetitions":1,"questions":[{"isParentQuestion":"false","question":"Procedure","questionId":"2551.1000043","options":[{"optionId":"2552.1000043","text":"Appendectomy","isInitiallySelected":false,"responseMode":"choice"},{"optionId":"2554.1000043","text":"Appendectomy and right colectomy","isInitiallySelected":false,"responseMode":"choice"},{"optionId":"2557.1000043","text":"Other (specify)","isInitiallySelected":false,"responseType":"string","defaultValue":"","minLength":0,"maxLength":80,"responseMode":"responseText","isRequired":true}],"maxSelections":1,"minSelections":1,"type":"SelectQuestion","minRepetitions":1,"maxRepetitions":1,"isRequired":true}]},{"title":"TUMOR","minRepetitions":1,"maxRepetitions":1,"questions":[{"isParentQuestion":"false","question":"Tumor Site (Note B)","questionId":"2581.1000043","options":[{"optionId":"2582.1000043","text":"Proximal half of appendix","isInitiallySelected":false,"controlledQuestions":[{"isParentQuestion":"false","question":"","questionId":"19718.1000043","options":[{"optionId":"18400.1000043","text":"Base of appendix involved by tumor","isInitiallySelected":false,"responseMode":"choice"},{"optionId":"18403.1000043","text":"Base of appendix uninvolved by tumor","isInitiallySelected":false,"responseMode":"choice"},{"optionId":"18402.1000043","text":"Involvement of base of appendix cannot be assessed","isInitiallySelected":false,"responseType":"string","defaultValue":"","minLength":0,"maxLength":80,"responseMode":"responseText","isRequired":false}],"maxSelections":1,"minSelections":1,"type":"SelectQuestion","minRepetitions":1,"maxRepetitions":1,"isRequired":false}],"responseMode":"choice"},{"optionId":"2587.1000043","text":"Distal half of appendix","isInitiallySelected":false,"responseMode":"choice"},{"optionId":"2588.1000043","text":"Diffusely involving appendix","isInitiallySelected":false,"responseMode":"choice"},{"optionId":"2589.1000043","text":"Appendix, not otherwise specified","isInitiallySelected":false,"responseMode":"choice"},{"optionId":"18404.1000043","text":"Other (specify)","isInitiallySelected":false,"responseType":"string","defaultValue":"","minLength":0,"maxLength":80,"responseMode":"responseText","isRequired":true}],"maxSelections":0,"minSelections":1,"type":"SelectQuestion","minRepetitions":1,"maxRepetitions":1,"isRequired":false},{"isParentQuestion":"true","subQuestions":[{"question":"Histologic Type Comments","questionId":"35587.1000043","type":"ResponseQuestion","minRepetitions":1,"maxRepetitions":1,"isRequired":false,"responseType":"string","defaultValue":"","minLength":0,"maxLength":80,"isParentQuestion":"false"}],"question":"Histologic Type (Note C)","questionId":"51493.1000043","options":[{"optionId":"2643.1000043","text":"Adenocarcinoma","isInitiallySelected":false,"responseMode":"choice"},{"optionId":"2644.1000043","text":"Mucinous adenocarcinoma","isInitiallySelected":false,"responseMode":"choice"},{"optionId":"34236.1000043","text":"Low-grade appendiceal mucinous neoplasm","isInitiallySelected":false,"responseMode":"choice"},{"optionId":"34237.1000043","text":"High-grade appendiceal mucinous neoplasm","isInitiallySelected":false,"responseMode":"choice"},{"optionId":"2645.1000043","text":"Signet-ring cell carcinoma","isInitiallySelected":false,"responseMode":"choice"},{"optionId":"34238.1000043","text":"Goblet cell carcinoid","isInitiallySelected":false,"responseMode":"choice"},{"optionId":"58967.1000043","text":"Mixed goblet cell carcinoid-adenocarcinoma (adenocarcinoma ex goblet cell carcinoid)","isInitiallySelected":false,"responseMode":"choice"},{"optionId":"55741.1000043","text":"Large cell neuroendocrine tumor","isInitiallySelected":false,"responseMode":"choice"},{"optionId":"59159.1000043","text":"Small cell neuroendocrine tumor","isInitiallySelected":false,"responseMode":"choice"},{"optionId":"51224.1000043","text":"Neuroendocrine carcinoma (poorly differentiated)#","isInitiallySelected":false,"responseMode":"choice"},{"optionId":"34239.1000043","text":"Mixed adenoneuroendocrine carcinoma","isInitiallySelected":false,"responseMode":"choice"},{"optionId":"51021.1000043","text":"Medullary carcinoma","isInitiallySelected":false,"responseMode":"choice"},{"optionId":"42631.1000043","text":"Adenosquamous carcinoma","isInitiallySelected":false,"responseMode":"choice"},{"optionId":"2647.1000043","text":"Undifferentiated carcinoma","isInitiallySelected":false,"responseMode":"choice"},{"optionId":"2648.1000043","text":"Other histologic type not listed (specify)","isInitiallySelected":false,"responseType":"string","defaultValue":"","minLength":0,"maxLength":80,"responseMode":"responseText","isRequired":true},{"optionId":"2649.1000043","text":"Carcinoma, type cannot be determined (explain)","isInitiallySelected":false,"responseType":"string","defaultValue":"","minLength":0,"maxLength":80,"responseMode":"responseText","isRequired":true}],"maxSelections":1,"minSelections":1,"type":"SelectQuestion","minRepetitions":1,"maxRepetitions":1,"isRequired":true},{"isParentQuestion":"false","question":"Histologic Grade (Note D)","questionId":"47240.1000043","options":[{"optionId":"2659.1000043","text":"G1: Well differentiated","isInitiallySelected":false,"responseMode":"choice"},{"optionId":"2660.1000043","text":"G2: Moderately differentiated","isInitiallySelected":false,"responseMode":"choice"},{"optionId":"2661.1000043","text":"G3: Poorly differentiated","isInitiallySelected":false,"responseMode":"choice"},{"optionId":"55066.1000043","text":"Other (specify)","isInitiallySelected":false,"responseType":"string","defaultValue":"","minLength":0,"maxLength":80,"responseMode":"responseText","isRequired":true},{"optionId":"2658.1000043","text":"GX: Cannot be assessed","isInitiallySelected":false,"responseType":"string","defaultValue":"","minLength":0,"maxLength":80,"responseMode":"responseText","isRequired":false},{"optionId":"2651.1000043","text":"Not applicable","isInitiallySelected":false,"responseType":"string","defaultValue":"","minLength":0,"maxLength":80,"responseMode":"responseText","isRequired":false}],"maxSelections":1,"minSelections":1,"type":"SelectQuestion","minRepetitions":1,"maxRepetitions":1,"isRequired":true},{"isParentQuestion":"false","question":"Tumor Size","questionId":"2590.1000043","options":[{"optionId":"2592.1000043","text":"Greatest dimension in Centimeters (cm)","isInitiallySelected":false,"responseSuffix":"cm","defaultValue":"","responseType":"decimal","responseMode":"responseText","isRequired":true},{"optionId":"2591.1000043","text":"Cannot be determined (explain)","isInitiallySelected":false,"responseType":"string","defaultValue":"","minLength":0,"maxLength":80,"responseMode":"responseText","isRequired":true}],"maxSelections":1,"minSelections":1,"type":"SelectQuestion","minRepetitions":1,"maxRepetitions":1,"isRequired":true},{"isParentQuestion":"false","question":"Tumor Deposits (Note G)","questionId":"2328.1000043","options":[{"optionId":"2330.1000043","text":"Not identified","isInitiallySelected":false,"responseMode":"choice"},{"optionId":"2331.1000043","text":"Present","isInitiallySelected":false,"controlledQuestions":[{"isParentQuestion":"false","question":"Specify Number of Deposits","questionId":"56191.1000043","options":[{"optionId":"56394.1000043","text":"Specify number","isInitiallySelected":false,"responseType":"integer","defaultValue":"1","minIntValue":1,"maxIntValue":100,"responseMode":"responseText","isRequired":true},{"optionId":"37814.1000043","text":"Number of tumor deposits cannot be determined (explain)","isInitiallySelected":false,"responseType":"string","defaultValue":"","minLength":0,"maxLength":80,"responseMode":"responseText","isRequired":true}],"maxSelections":1,"minSelections":1,"type":"SelectQuestion","minRepetitions":1,"maxRepetitions":1,"isRequired":true}],"responseMode":"choice"},{"optionId":"2329.1000043","text":"Cannot be determined","isInitiallySelected":false,"responseType":"string","defaultValue":"","minLength":0,"maxLength":80,"responseMode":"responseText","isRequired":false}],"maxSelections":1,"minSelections":1,"type":"SelectQuestion","minRepetitions":1,"maxRepetitions":1,"isRequired":true},{"isParentQuestion":"false","question":"Tumor Extension","questionId":"46567.1000043","options":[{"optionId":"2315.1000043","text":"No evidence of primary tumor","isInitiallySelected":false,"responseMode":"choice"},{"optionId":"43289.1000043","text":"Tumor invades lamina propria or muscularis mucosa","isInitiallySelected":false,"responseMode":"choice"},{"optionId":"2318.1000043","text":"Tumor invades submucosa","isInitiallySelected":false,"responseMode":"choice"},{"optionId":"2319.1000043","text":"Tumor invades muscularis propria","isInitiallySelected":false,"responseMode":"choice"},{"optionId":"51442.1000043","text":"Acellular mucin invades subserosa or mesoappendix but does not extend to the serosal surface","isInitiallySelected":false,"responseMode":"choice"},{"optionId":"2320.1000043","text":"Tumor invades through the muscularis propria into the subserosa or mesoappendix but does not extend to the serosal surface","isInitiallySelected":false,"responseMode":"choice"},{"optionId":"42800.1000043","text":"Acellular mucin invades the visceral peritoneum (serosa)","isInitiallySelected":false,"responseMode":"choice"},{"optionId":"43058.1000043","text":"Tumor invades the visceral peritoneum (serosa)","isInitiallySelected":false,"responseMode":"choice"},{"optionId":"2322.1000043","text":"Tumor directly invades adjacent organs or structures (specify)","isInitiallySelected":false,"responseType":"string","defaultValue":"","minLength":0,"maxLength":80,"responseMode":"responseText","isRequired":true},{"optionId":"2314.1000043","text":"Cannot be assessed","isInitiallySelected":false,"responseType":"string","defaultValue":"","minLength":0,"maxLength":80,"responseMode":"responseText","isRequired":false}],"maxSelections":0,"minSelections":1,"type":"SelectQuestion","minRepetitions":1,"maxRepetitions":1,"isRequired":true},{"isParentQuestion":"false","question":"Lymphovascular Invasion (Note F)","questionId":"2713.1000043","options":[{"optionId":"2714.1000043","text":"Not identified","isInitiallySelected":false,"responseMode":"choice"},{"optionId":"2715.1000043","text":"Present","isInitiallySelected":false,"responseMode":"choice"},{"optionId":"2719.1000043","text":"Cannot be determined","isInitiallySelected":false,"responseType":"string","defaultValue":"","minLength":0,"maxLength":80,"responseMode":"responseText","isRequired":false}],"maxSelections":1,"minSelections":1,"type":"SelectQuestion","minRepetitions":1,"maxRepetitions":1,"isRequired":true},{"isParentQuestion":"false","question":"Perineural Invasion (Note H)","questionId":"2727.1000043","options":[{"optionId":"2728.1000043","text":"Not identified","isInitiallySelected":false,"responseMode":"choice"},{"optionId":"2729.1000043","text":"Present","isInitiallySelected":false,"responseMode":"choice"},{"optionId":"2334.1000043","text":"Cannot be determined","isInitiallySelected":false,"responseType":"string","defaultValue":"","minLength":0,"maxLength":80,"responseMode":"responseText","isRequired":false}],"maxSelections":1,"minSelections":1,"type":"SelectQuestion","minRepetitions":1,"maxRepetitions":1,"isRequired":false}]},{"title":"MARGINS (Note E)","minRepetitions":1,"maxRepetitions":1,"sections":[{"title":"Other Margin(s) (repeat as needed)","minRepetitions":1,"maxRepetitions":1,"questions":[{"question":"?Specify Margin","questionId":"44115.1000043","type":"ResponseQuestion","minRepetitions":1,"maxRepetitions":10,"isRequired":true,"responseType":"string","defaultValue":"","minLength":0,"maxLength":80,"isParentQuestion":"true","subQuestions":[{"isParentQuestion":"false","question":"Margin Status","questionId":"26648.1000043","options":[{"optionId":"26649.1000043","text":"Cannot be assessed","isInitiallySelected":false,"responseType":"string","defaultValue":"","minLength":0,"maxLength":80,"responseMode":"responseText","isRequired":false},{"optionId":"26650.1000043","text":"Uninvolved by invasive carcinoma","isInitiallySelected":false,"responseMode":"choice"},{"optionId":"26651.1000043","text":"Involved by invasive carcinoma","isInitiallySelected":false,"responseMode":"choice"}],"maxSelections":1,"minSelections":1,"type":"SelectQuestion","minRepetitions":1,"maxRepetitions":1,"isRequired":true}]}]}],"questions":[{"isParentQuestion":"false","question":"Proximal Margin","questionId":"33686.1000043","options":[{"optionId":"33687.1000043","text":"Cannot be assessed","isInitiallySelected":false,"responseType":"string","defaultValue":"","minLength":0,"maxLength":80,"responseMode":"responseText","isRequired":false},{"optionId":"33688.1000043","text":"Uninvolved by invasive carcinoma","isInitiallySelected":false,"controlledQuestions":[{"isParentQuestion":"false","question":"","questionId":"34256.1000043","options":[{"optionId":"34853.1000043","text":"Involved by high-grade dysplasia","isInitiallySelected":false,"responseMode":"choice"}],"maxSelections":0,"minSelections":1,"type":"SelectQuestion","minRepetitions":1,"maxRepetitions":1,"isRequired":true},{"isParentQuestion":"false","question":"","questionId":"39414.1000043","options":[{"optionId":"57419.1000043","text":"Involved by acellular mucin","isInitiallySelected":false,"responseMode":"choice"}],"maxSelections":0,"minSelections":1,"type":"SelectQuestion","minRepetitions":1,"maxRepetitions":1,"isRequired":true},{"isParentQuestion":"false","question":"?Status of Mucinous Neoplasm at Proximal Margin","questionId":"33690.1000043","options":[{"optionId":"47065.1000043","text":"?Not applicable","isInitiallySelected":false,"responseMode":"choice"},{"optionId":"33694.1000043","text":"Uninvolved by appendiceal mucinous neoplasm","isInitiallySelected":false,"responseMode":"choice"},{"optionId":"33723.1000043","text":"Involved by low-grade appendiceal mucinous neoplasm","isInitiallySelected":false,"responseMode":"choice"},{"optionId":"34645.1000043","text":"Involved by high-grade appendiceal mucinous neoplasm","isInitiallySelected":false,"responseMode":"choice"}],"maxSelections":0,"minSelections":1,"type":"SelectQuestion","minRepetitions":1,"maxRepetitions":1,"isRequired":true}],"responseMode":"choice"},{"optionId":"33689.1000043","text":"Involved by invasive carcinoma","isInitiallySelected":false,"responseMode":"choice"}],"maxSelections":1,"minSelections":1,"type":"SelectQuestion","minRepetitions":1,"maxRepetitions":1,"isRequired":true},{"isParentQuestion":"false","question":"?Mesenteric Margin","questionId":"34854.1000043","options":[{"optionId":"34895.1000043","text":"?Not applicable","isInitiallySelected":false,"responseMode":"choice"},{"optionId":"34896.1000043","text":"Cannot be assessed","isInitiallySelected":false,"responseType":"string","defaultValue":"","minLength":0,"maxLength":80,"responseMode":"responseText","isRequired":false},{"optionId":"34897.1000043","text":"Uninvolved by invasive carcinoma","isInitiallySelected":false,"controlledQuestions":[{"isParentQuestion":"false","question":"","questionId":"56268.1000043","options":[{"optionId":"39348.1000043","text":"Involved by acellular mucin","isInitiallySelected":false,"responseMode":"choice"}],"maxSelections":0,"minSelections":1,"type":"SelectQuestion","minRepetitions":1,"maxRepetitions":1,"isRequired":true},{"isParentQuestion":"false","question":"?Status of Mucinous Neoplasm at Mesenteric Margin","questionId":"34905.1000043","options":[{"optionId":"48396.1000043","text":"?Not applicable","isInitiallySelected":false,"responseMode":"choice"},{"optionId":"34899.1000043","text":"Uninvolved by appendiceal mucinous neoplasm","isInitiallySelected":false,"responseMode":"choice"},{"optionId":"34904.1000043","text":"Involved by low-grade appendiceal mucinous neoplasm","isInitiallySelected":false,"responseMode":"choice"},{"optionId":"34908.1000043","text":"Involved by high- grade appendiceal mucinous neoplasm","isInitiallySelected":false,"responseMode":"choice"}],"maxSelections":0,"minSelections":1,"type":"SelectQuestion","minRepetitions":1,"maxRepetitions":1,"isRequired":true},{"isParentQuestion":"false","question":"Distance of Invasive Carcinoma from Closest Mesenteric Margin","questionId":"34909.1000043","options":[{"optionId":"34900.1000043","text":"Specify in Millimeters (mm)","isInitiallySelected":false,"responseSuffix":"mm","defaultValue":"","responseType":"decimal","responseMode":"responseText","isRequired":true},{"optionId":"34901.1000043","text":"Specify in Centimeters (cm)","isInitiallySelected":false,"responseSuffix":"cm","defaultValue":"","responseType":"decimal","responseMode":"responseText","isRequired":true},{"optionId":"34902.1000043","text":"Cannot be determined (explain)","isInitiallySelected":false,"responseType":"string","defaultValue":"","minLength":0,"maxLength":80,"responseMode":"responseText","isRequired":true}],"maxSelections":1,"minSelections":1,"type":"SelectQuestion","minRepetitions":1,"maxRepetitions":1,"isRequired":false}],"responseMode":"choice"},{"optionId":"34898.1000043","text":"Involved by invasive carcinoma","isInitiallySelected":false,"responseMode":"choice"}],"maxSelections":1,"minSelections":1,"type":"SelectQuestion","minRepetitions":1,"maxRepetitions":1,"isRequired":true}]},{"title":"LYMPH NODES","minRepetitions":1,"maxRepetitions":1,"questions":[{"isParentQuestion":"false","question":"Regional Lymph Nodes","questionId":"2194.1000043","options":[{"optionId":"2195.1000043","text":"No lymph nodes submitted or found","isInitiallySelected":false,"controlledQuestions":[{"isParentQuestion":"false","question":"Number of Lymph Nodes Involved","questionId":"34184.1000043","options":[{"optionId":"2200.1000043","text":"Specify number","isInitiallySelected":false,"responseType":"integer","defaultValue":"0","minIntValue":0,"maxIntValue":100,"responseMode":"responseText","isRequired":true},{"optionId":"34088.1000043","text":"At least","isInitiallySelected":false,"responseType":"integer","defaultValue":"1","minIntValue":1,"maxIntValue":100,"responseMode":"responseText","isRequired":true},{"optionId":"2201.1000043","text":"Number cannot be determined (explain)","isInitiallySelected":false,"responseType":"string","defaultValue":"","minLength":0,"maxLength":80,"responseMode":"responseText","isRequired":true}],"maxSelections":1,"minSelections":1,"type":"SelectQuestion","minRepetitions":1,"maxRepetitions":1,"isRequired":true},{"isParentQuestion":"false","question":"Number of Lymph Nodes Examined","questionId":"34183.1000043","options":[{"optionId":"2197.1000043","text":"Specify number","isInitiallySelected":false,"responseType":"integer","defaultValue":"0","minIntValue":0,"maxIntValue":100,"responseMode":"responseText","isRequired":true},{"optionId":"34087.1000043","text":"At least","isInitiallySelected":false,"responseType":"integer","defaultValue":"1","minIntValue":1,"maxIntValue":100,"responseMode":"responseText","isRequired":true},{"optionId":"2198.1000043","text":"Number cannot be determined (explain)","isInitiallySelected":false,"responseType":"string","defaultValue":"","minLength":0,"maxLength":80,"responseMode":"responseText","isRequired":true}],"maxSelections":1,"minSelections":1,"type":"SelectQuestion","minRepetitions":1,"maxRepetitions":1,"isRequired":true}],"responseMode":"choice"}],"maxSelections":0,"minSelections":1,"type":"SelectQuestion","minRepetitions":1,"maxRepetitions":1,"isRequired":true}]},{"title":"PATHOLOGIC STAGE CLASSIFICATION (pTNM, AJCC 8th Edition) (Note I)","minRepetitions":1,"maxRepetitions":1,"questions":[{"isParentQuestion":"false","question":"?TNM Descriptors","questionId":"2336.1000043","options":[{"optionId":"3821.1000043","text":"?Not applicable","isInitiallySelected":false,"responseType":"string","defaultValue":"","minLength":0,"maxLength":80,"responseMode":"responseText","isRequired":false},{"optionId":"2337.1000043","text":"m (multiple primary tumors)","isInitiallySelected":false,"responseMode":"choice"},{"optionId":"2338.1000043","text":"r (recurrent)","isInitiallySelected":false,"responseMode":"choice"},{"optionId":"2339.1000043","text":"y (post-treatment)","isInitiallySelected":false,"responseMode":"choice"}],"maxSelections":0,"minSelections":1,"type":"SelectQuestion","minRepetitions":1,"maxRepetitions":1,"isRequired":true},{"isParentQuestion":"false","question":"Primary Tumor (pT)","questionId":"50624.1000043","options":[{"optionId":"37690.1000043","text":"pTX: Primary tumor cannot be assessed","isInitiallySelected":false,"responseMode":"choice"},{"optionId":"37691.1000043","text":"pT0: No evidence of primary tumor","isInitiallySelected":false,"responseMode":"choice"},{"optionId":"37692.1000043","text":"pTis: Carcinoma in situ (intramucosal carcinoma; invasion of the lamina propria or extension into but not through the muscularis mucosae)","isInitiallySelected":false,"responseMode":"choice"},{"optionId":"37693.1000043","text":"pTis (LAMN): Low-grade appendiceal mucinous neoplasm confined by the muscularis propria. Acellular mucin or mucinous epithelium may invade into the muscularis propria. (T1 and T2 are not applicable to LAMN. Acellular mucin or mucinous epithelium that extends into the subserosa or serosa should be classified as T3 or T4a, respectively.)","isInitiallySelected":false,"responseMode":"choice"},{"optionId":"37694.1000043","text":"pT1: Tumor invades the submucosa (through the muscularis mucosa but not into the muscularis propria)","isInitiallySelected":false,"responseMode":"choice"},{"optionId":"37695.1000043","text":"pT2: Tumor invades the muscularis propria","isInitiallySelected":false,"responseMode":"choice"},{"optionId":"37696.1000043","text":"pT3: Tumor invades through the muscularis propria into the subserosa or the mesoappendix","isInitiallySelected":false,"responseMode":"choice"},{"optionId":"37698.1000043","text":"pT4a: Tumor invades through the visceral peritoneum, including the acellular mucin or mucinous epithelium involving the serosa of the appendix or serosa of the mesoappendix","isInitiallySelected":false,"responseMode":"choice"},{"optionId":"37699.1000043","text":"pT4b: Tumor directly invades (or adheres to#) adjacent organs or structures","isInitiallySelected":false,"responseMode":"choice"},{"optionId":"47544.1000043","text":"pT4 (subcategory cannot be determined)","isInitiallySelected":false,"responseMode":"choice"}],"maxSelections":1,"minSelections":1,"type":"SelectQuestion","minRepetitions":1,"maxRepetitions":1,"isRequired":true},{"isParentQuestion":"false","question":"Regional Lymph Nodes (pN)","questionId":"55702.1000043","options":[{"optionId":"37701.1000043","text":"pNX: Regional lymph nodes cannot be assessed","isInitiallySelected":false,"responseMode":"choice"},{"optionId":"37702.1000043","text":"pN0: No regional lymph node metastasis","isInitiallySelected":false,"responseMode":"choice"},{"optionId":"37704.1000043","text":"pN1a: One regional lymph node is positive","isInitiallySelected":false,"responseMode":"choice"},{"optionId":"37705.1000043","text":"pN1b: Two or three regional lymph nodes are positive","isInitiallySelected":false,"responseMode":"choice"},{"optionId":"37706.1000043","text":"pN1c: No regional lymph nodes are positive, but there are tumor deposits in the subserosa or mesentery","isInitiallySelected":false,"responseMode":"choice"},{"optionId":"41842.1000043","text":"pN1 (subcategory cannot be determined)","isInitiallySelected":false,"responseMode":"choice"},{"optionId":"37707.1000043","text":"pN2: Four or more regional lymph nodes are positive","isInitiallySelected":false,"responseMode":"choice"}],"maxSelections":1,"minSelections":1,"type":"SelectQuestion","minRepetitions":1,"maxRepetitions":1,"isRequired":true},{"isParentQuestion":"true","subQuestions":[{"question":"?Specify Site(s), if known","questionId":"37713.1000043","type":"ResponseQuestion","minRepetitions":1,"maxRepetitions":1,"isRequired":true,"responseType":"string","defaultValue":"","minLength":0,"maxLength":80,"isParentQuestion":"false"}],"question":"?Distant Metastasis (pM)","questionId":"53000.1000043","options":[{"optionId":"37709.1000043","text":"?Not applicable - pM cannot be determined from the submitted specimen(s)","isInitiallySelected":false,"responseMode":"choice"},{"optionId":"37711.1000043","text":"pM1a: Intraperitoneal acellular mucin, without identifiable tumor cells in the disseminated peritoneal mucinous deposits","isInitiallySelected":false,"responseMode":"choice"},{"optionId":"37712.1000043","text":"pM1b: Intraperitoneal metastasis only, including peritoneal mucinous deposits containing tumor cells","isInitiallySelected":false,"responseMode":"choice"},{"optionId":"37680.1000043","text":"pM1c: Metastasis to sites other than peritoneum","isInitiallySelected":false,"responseMode":"choice"},{"optionId":"44006.1000043","text":"pM1 (subcategory cannot be determined)","isInitiallySelected":false,"responseMode":"choice"}],"maxSelections":1,"minSelections":1,"type":"SelectQuestion","minRepetitions":1,"maxRepetitions":1,"isRequired":true}]},{"title":"ADDITIONAL FINDINGS (Note J)","minRepetitions":1,"maxRepetitions":1,"questions":[{"isParentQuestion":"false","question":"Additional Pathologic Findings","questionId":"37670.1000043","options":[{"optionId":"2731.1000043","text":"None identified","isInitiallySelected":false,"responseMode":"choice"},{"optionId":"2732.1000043","text":"Appendicitis","isInitiallySelected":false,"responseMode":"choice"},{"optionId":"2762.1000043","text":"Perforation, not at tumor","isInitiallySelected":false,"responseMode":"choice"},{"optionId":"43384.1000043","text":"Ulcerative colitis","isInitiallySelected":false,"responseMode":"choice"},{"optionId":"2764.1000043","text":"Crohn disease","isInitiallySelected":false,"responseMode":"choice"},{"optionId":"2765.1000043","text":"Diverticulosis","isInitiallySelected":false,"responseMode":"choice"},{"optionId":"2777.1000043","text":"Other (specify)","isInitiallySelected":false,"responseType":"string","defaultValue":"","minLength":0,"maxLength":80,"responseMode":"responseText","isRequired":true}],"maxSelections":0,"minSelections":1,"type":"SelectQuestion","minRepetitions":1,"maxRepetitions":1,"isRequired":false}]},{"title":"SPECIAL STUDIES (Note K)","minRepetitions":1,"maxRepetitions":1,"questions":[{"isParentQuestion":"false","question":"Ancillary Studies","questionId":"18390.1000043","options":[{"optionId":"2349.1000043","text":"Performed (specify)","isInitiallySelected":false,"responseType":"string","defaultValue":"","minLength":0,"maxLength":80,"responseMode":"responseText","isRequired":true},{"optionId":"2350.1000043","text":"Not performed","isInitiallySelected":false,"responseMode":"choice"}],"maxSelections":1,"minSelections":1,"type":"SelectQuestion","minRepetitions":1,"maxRepetitions":1,"isRequired":false}]}],"questions":[{"question":"?Comment(s)","questionId":"2778.1000043","type":"ResponseQuestion","minRepetitions":1,"maxRepetitions":1,"isRequired":true,"responseType":"string","defaultValue":"","minLength":0,"maxLength":80,"isParentQuestion":"false"}]},"footer":{"CopyrightFooter":"(c) 2019 College of American Pathologists.  All rights reserved.  License required for use."},"diagnosticProcedureId":"Appendix.Res.135"}